percent_password/__init__.py
percent_password/pwgv.py
percent_password-1.0.dist-info/METADATA
percent_password-1.0.dist-info/WHEEL
percent_password-1.0.dist-info/top_level.txt
percent_password-1.0.dist-info/RECORD
