Metadata-Version: 2.1
Name: percent_password
Version: 1.0
Summary: Pwgv (password generation and verification) генерация и проверка паролей
Home-page: https://github.com/G0ga1/percent_password
Author: testg1
Author-email: radan85669@avashost.com
Classifier: Programming Language :: Python :: 3
Classifier: Programming Language :: Python :: 3.12
Classifier: Operating System :: OS Independent
Classifier: Development Status :: 4 - Beta
Classifier: Intended Audience :: Developers
Classifier: Topic :: Software Development :: Libraries :: Python Modules
Requires-Python: >=3.12
